pykdclient/__about__.py
pykdclient/__init__.py
pykdclient/constants.py
pykdclient/debug_connection.py
pykdclient/debug_context.py
pykdclient/kd_packet.py
pykdclient/server.py
pykdclient/sniffer.py
pykdclient/util.py
pykdclient/windpl.py
pykdclient/windpl_extra.py
pykdclient/windpl_loop.py
pykdclient-0.1.1.dist-info/METADATA
pykdclient-0.1.1.dist-info/WHEEL
pykdclient-0.1.1.dist-info/entry_points.txt
pykdclient-0.1.1.dist-info/licenses/LICENSE.md
pykdclient-0.1.1.dist-info/RECORD
