Metadata-Version: 2.4
Name: pykdclient
Version: 0.1.1
Summary: Basic tool to capture Microsoft Xbox (original) debug messages sent via the KD protocol.
Project-URL: Documentation, https://github.com/abaire/pykdclient#readme
Project-URL: Issues, https://github.com/abaire/pykdclient/issues
Project-URL: Source, https://github.com/abaire/pykdclient
Author-email: Erik Abair <erik.abair@bearbrains.work>
License: ### GNU GENERAL PUBLIC LICENSE
License-File: LICENSE.md
Keywords: xbox,xemu
Classifier: Development Status :: 3 - Alpha
Classifier: Environment :: Console
Classifier: Intended Audience :: Developers
Classifier: Operating System :: OS Independent
Classifier: Programming Language :: Python
Classifier: Programming Language :: Python :: 3.10
Classifier: Programming Language :: Python :: 3.11
Classifier: Programming Language :: Python :: 3.12
Classifier: Topic :: Software Development :: Documentation
Requires-Python: >=3.10
